MANIFEST.in
README.rst
setup.py
pypilist/__init__.py
pypilist/packages.json
pypilist/pypi.py
pypilist.egg-info/PKG-INFO
pypilist.egg-info/SOURCES.txt
pypilist.egg-info/dependency_links.txt
pypilist.egg-info/entry_points.txt
pypilist.egg-info/requires.txt
pypilist.egg-info/top_level.txt